{"date":"2026-06-27","heading":"Samedi 27 juin","scripture":"Continuez à les élever conformément aux principes et aux avertissements de Jéhovah","scriptureReference":"Éph. 6:4","commentary":"Quand un mineur, c’est-à-dire un jeune de moins de 18 ans, commet un péché grave alors qu’il est baptisé, comment les anciens doivent-ils traiter l’affaire ? Le collège des anciens désignera deux de ses membres pour s’entretenir avec le jeune et avec ses parents s’ils sont Témoins de Jéhovah. Les deux anciens demanderont aux parents quelles dispositions ils ont prises pour aider leur enfant à se repentir. Si le mineur manifeste un bon état d’esprit et si ses parents parviennent à toucher son cœur, les anciens estimeront peut-être qu’il n’est pas nécessaire d’entreprendre une autre démarche. En effet, c’est aux parents que Dieu a donné la responsabilité de corriger leurs enfants avec amour (Deut. 6:6, 7 ; Prov. 6:20 ; 22:6 ; Éph. 6:2-4). Ensuite, les anciens discuteront de temps en temps avec les parents pour s’assurer que leur enfant reçoit bien l’aide dont il a besoin. Et si un mineur baptisé ne se repent pas et qu’il continue de pratiquer le mal ? Dans ce cas, un comité d’anciens s’entretiendra avec lui et avec ses parents s’ils sont Témoins de Jéhovah.","commentarySource":"w24.08 24 § 18","publicationTitle":"Examinons les Écritures chaque jour 2026","wolUrl":"https://wol.jw.org/wol/d/r30/lp-f/1102026205?#h=80:0-83:0","jwOrgUrl":"https://www.jw.org/finder?alias=daily-text&date=20260627&wtlocale=F&srcid=jwlshare","questions":[{"id":"jw-dt-q1","question":"Le verset « Continuez à les élever conformément aux principes et… » (Éph. 6:4) vous invite aujourd'hui à…","options":["Le verset invite à se concentrer sur les inquiétudes matérielles.","Douter que Jéhovah s'intéresse à notre situation.","Ce verset concerne uniquement la vie future, pas notre quotidien.","Le collège des anciens désignera deux de ses membres pour s’entretenir avec le jeune et avec ses…"],"correctIndex":3,"explanation":"« Continuez à les élever conformément aux principes et aux avertissements de Jéhovah » — Éph. 6:4. Le collège des anciens désignera deux de ses membres pour s’entretenir avec le jeune et avec ses parents s’ils sont Témoins de Jéhovah."}]}